adprompt/__init__.py
adprompt/client.py
adprompt/rerank.py
adprompt/utils/__init__.py
adprompt/utils/json_utils.py
adprompt/utils/lib_utils.py
adprompt-0.8.dist-info/licenses/LICENSE.txt
adprompt-0.8.dist-info/WHEEL
adprompt-0.8.dist-info/METADATA
adprompt-0.8.dist-info/RECORD
